{
  "type": "Container",
  "props": {
    "canDelete": true,
    "canEditName": true,
    "type": "section",
    "custom": {
      "displayName": "Features Image List CTAs"
    },
    "className": "bg-(--background) text-(--foreground) w-full py-(--space-lg) px-(--container-padding-x)"
  },
  "children": [
    {
      "type": "Container",
      "props": {
        "canDelete": true,
        "canEditName": true,
        "custom": {
          "displayName": "Section Inner"
        },
        "className": "flex flex-col gap-(--space-md) w-full max-w-6xl mx-auto items-start md:flex-row md:items-start"
      },
      "children": [
        {
          "type": "Image",
          "props": {
            "content": "https://images.unsplash.com/photo-1522071820081-009f0129c71c?w=800&h=960&fit=crop",
            "alt": "Team collaborating at a table with laptops",
            "custom": {
              "displayName": "Feature Image"
            },
            "className": "rounded-2xl w-full h-72 object-cover md:w-1/2 md:h-full md:min-h-[28rem] md:object-cover"
          }
        },
        {
          "type": "Container",
          "props": {
            "canDelete": true,
            "canEditName": true,
            "custom": {
              "displayName": "Content Column"
            },
            "className": "flex flex-col gap-(--space-md) w-full md:w-1/2 md:flex-1"
          },
          "children": [
            {
              "type": "Container",
              "props": {
                "canDelete": true,
                "canEditName": true,
                "custom": {
                  "displayName": "Intro"
                },
                "className": "flex flex-col gap-(--space-sm) w-full"
              },
              "children": [
                {
                  "type": "Text",
                  "props": {
                    "text": "Designed for business teams",
                    "tagName": "h2",
                    "custom": {
                      "displayName": "Heading"
                    },
                    "className": "font-bold leading-tight text-3xl md:text-4xl font-(--heading-font-family)"
                  }
                },
                {
                  "type": "Text",
                  "props": {
                    "text": "Ship updates with confidence: keep marketing, design, and engineering aligned without turning every tweak into a ticket queue.",
                    "tagName": "p",
                    "custom": {
                      "displayName": "Intro"
                    },
                    "className": "text-(--muted-foreground) text-base leading-relaxed"
                  }
                }
              ]
            },
            {
              "type": "Container",
              "props": {
                "canDelete": true,
                "canEditName": true,
                "custom": {
                  "displayName": "Feature List"
                },
                "className": "flex flex-col w-full"
              },
              "children": [
                {
                  "type": "Container",
                  "props": {
                    "canDelete": true,
                    "canEditName": true,
                    "custom": {
                      "displayName": "Feature — Security"
                    },
                    "className": "flex flex-row gap-(--space-sm) w-full items-start py-(--space-md)"
                  },
                  "children": [
                    {
                      "type": "Container",
                      "props": {
                        "canDelete": true,
                        "canEditName": true,
                        "custom": {
                          "displayName": "Icon 1"
                        },
                        "className": "bg-(--primary) text-(--primary-foreground) rounded-full flex w-12 h-12 min-w-12 items-center justify-center"
                      },
                      "children": [
                        {
                          "type": "Text",
                          "props": {
                            "text": "L",
                            "tagName": "span",
                            "custom": {
                              "displayName": "Glyph"
                            },
                            "className": "font-bold text-sm"
                          }
                        }
                      ]
                    },
                    {
                      "type": "Container",
                      "props": {
                        "canDelete": true,
                        "canEditName": true,
                        "custom": {
                          "displayName": "Copy 1"
                        },
                        "className": "flex flex-col gap-(--space-xs) flex-1"
                      },
                      "children": [
                        {
                          "type": "Text",
                          "props": {
                            "text": "Keep your data secure",
                            "tagName": "h3",
                            "custom": {
                              "displayName": "Title"
                            },
                            "className": "font-semibold text-lg leading-snug"
                          }
                        },
                        {
                          "type": "Text",
                          "props": {
                            "text": "Granular access, sane defaults, and clear audit trails so the right people can publish without opening the floodgates.",
                            "tagName": "p",
                            "custom": {
                              "displayName": "Description"
                            },
                            "className": "text-(--muted-foreground) text-sm leading-relaxed"
                          }
                        },
                        {
                          "type": "Button",
                          "props": {
                            "text": "Learn more >",
                            "url": "#",
                            "custom": {
                              "displayName": "CTA 1"
                            },
                            "className": "bg-transparent text-(--primary) text-sm font-semibold px-(--container-padding-x) py-(--space-xs) mt-1"
                          }
                        }
                      ]
                    }
                  ]
                },
                {
                  "type": "Container",
                  "props": {
                    "canDelete": true,
                    "canEditName": true,
                    "custom": {
                      "displayName": "Feature — Insight"
                    },
                    "className": "border-t border-(--muted) flex flex-row gap-(--space-sm) w-full items-start py-(--space-md)"
                  },
                  "children": [
                    {
                      "type": "Container",
                      "props": {
                        "canDelete": true,
                        "canEditName": true,
                        "custom": {
                          "displayName": "Icon 2"
                        },
                        "className": "bg-(--accent) text-(--accent-foreground) rounded-full flex w-12 h-12 min-w-12 items-center justify-center"
                      },
                      "children": [
                        {
                          "type": "Text",
                          "props": {
                            "text": "M",
                            "tagName": "span",
                            "custom": {
                              "displayName": "Glyph"
                            },
                            "className": "font-bold text-sm"
                          }
                        }
                      ]
                    },
                    {
                      "type": "Container",
                      "props": {
                        "canDelete": true,
                        "canEditName": true,
                        "custom": {
                          "displayName": "Copy 2"
                        },
                        "className": "flex flex-col gap-(--space-xs) flex-1"
                      },
                      "children": [
                        {
                          "type": "Text",
                          "props": {
                            "text": "Insights at a glance",
                            "tagName": "h3",
                            "custom": {
                              "displayName": "Title"
                            },
                            "className": "font-semibold text-lg leading-snug"
                          }
                        },
                        {
                          "type": "Text",
                          "props": {
                            "text": "Connect analytics once, then see what resonates—from first visit to conversion—without exporting spreadsheets every Monday.",
                            "tagName": "p",
                            "custom": {
                              "displayName": "Description"
                            },
                            "className": "text-(--muted-foreground) text-sm leading-relaxed"
                          }
                        },
                        {
                          "type": "Button",
                          "props": {
                            "text": "Learn more >",
                            "url": "#",
                            "custom": {
                              "displayName": "CTA 2"
                            },
                            "className": "bg-transparent text-(--accent) text-sm font-semibold px-(--container-padding-x) py-(--space-xs) mt-1"
                          }
                        }
                      ]
                    }
                  ]
                },
                {
                  "type": "Container",
                  "props": {
                    "canDelete": true,
                    "canEditName": true,
                    "custom": {
                      "displayName": "Feature — Build"
                    },
                    "className": "border-t border-(--muted) flex flex-row gap-(--space-sm) w-full items-start py-(--space-md)"
                  },
                  "children": [
                    {
                      "type": "Container",
                      "props": {
                        "canDelete": true,
                        "canEditName": true,
                        "custom": {
                          "displayName": "Icon 3"
                        },
                        "className": "bg-(--secondary) text-(--secondary-foreground) rounded-full flex w-12 h-12 min-w-12 items-center justify-center"
                      },
                      "children": [
                        {
                          "type": "Text",
                          "props": {
                            "text": "C",
                            "tagName": "span",
                            "custom": {
                              "displayName": "Glyph"
                            },
                            "className": "font-bold text-sm"
                          }
                        }
                      ]
                    },
                    {
                      "type": "Container",
                      "props": {
                        "canDelete": true,
                        "canEditName": true,
                        "custom": {
                          "displayName": "Copy 3"
                        },
                        "className": "flex flex-col gap-(--space-xs) flex-1"
                      },
                      "children": [
                        {
                          "type": "Text",
                          "props": {
                            "text": "Automate workflows",
                            "tagName": "h3",
                            "custom": {
                              "displayName": "Title"
                            },
                            "className": "font-semibold text-lg leading-snug"
                          }
                        },
                        {
                          "type": "Text",
                          "props": {
                            "text": "Hook up webhooks, forms, and your favorite tools so repetitive work happens in the background—not in someone’s inbox.",
                            "tagName": "p",
                            "custom": {
                              "displayName": "Description"
                            },
                            "className": "text-(--muted-foreground) text-sm leading-relaxed"
                          }
                        },
                        {
                          "type": "Button",
                          "props": {
                            "text": "Learn more >",
                            "url": "#",
                            "custom": {
                              "displayName": "CTA 3"
                            },
                            "className": "bg-transparent text-(--secondary) text-sm font-semibold px-(--container-padding-x) py-(--space-xs) mt-1"
                          }
                        }
                      ]
                    }
                  ]
                }
              ]
            }
          ]
        }
      ]
    }
  ]
}
