{
  "type": "Container",
  "props": {
    "canDelete": true,
    "canEditName": true,
    "type": "section",
    "root": {
      "background": "bg-(--background)",
      "color": "text-(--foreground)"
    },
    "mobile": {
      "display": "flex",
      "flexDirection": "flex-col",
      "alignItems": "items-center",
      "justifyContent": "justify-center",
      "width": "w-full",
      "py": "py-12",
      "px": "px-4"
    },
    "desktop": {
      "py": "py-16",
      "px": "px-6"
    },
    "custom": {
      "displayName": "Column Container Section"
    }
  },
  "children": [
    {
      "type": "Container",
      "props": {
        "canDelete": true,
        "canEditName": true,
        "root": {
          "background": "bg-(--muted)",
          "radius": "rounded-(--card-radius)",
          "color": "text-(--foreground)"
        },
        "mobile": {
          "py": "py-3",
          "px": "px-3",
          "mx": "mx-auto",
          "display": "flex",
          "justifyContent": "justify-end",
          "flexDirection": "flex-col",
          "width": "w-full",
          "maxWidth": "max-w-(--content-width)",
          "gap": "gap-3",
          "minHeight": "min-h-96",
          "backgroundSize": "bg-contain",
          "backgroundPosition": "bg-top",
          "backgroundRepeat": "bg-no-repeat",
          "overflow": "overflow-hidden"
        },
        "desktop": {
          "flexDirection": "flex-row",
          "minHeight": "min-h-screen",
          "height": "",
          "backgroundSize": "bg-cover",
          "backgroundPosition": "bg-bottom-left",
          "py": "",
          "px": "",
          "justifyContent": "justify-center",
          "alignItems": "items-end",
          "backgroundAttachment": "bg-fixed"
        },
        "backgroundImageType": "img",
        "backgroundImage": "https://imagedelivery.net/8PYt12v3QMuDRiYrOftNUQ/f4722fe1-53f8-4804-1d6c-2d3dac4cd000/public",
        "hidden": false,
        "custom": {
          "displayName": "Column Container"
        }
      },
      "children": [
        {
          "type": "Container",
          "props": {
            "canDelete": true,
            "canEditName": true,
            "root": {
              "color": "text-(--background)"
            },
            "mobile": {
              "py": "py-6",
              "px": "px-4",
              "display": "flex",
              "justifyContent": "justify-center",
              "flexDirection": "flex-col",
              "width": "w-full",
              "gap": "gap-4",
              "height": "h-auto",
              "maxWidth": "max-w-(--content-width)"
            },
            "desktop": {
              "width": "w-full",
              "maxWidth": "max-w-2xl",
              "py": "py-10",
              "px": "px-8",
              "my": "",
              "height": ""
            },
            "custom": {
              "displayName": "Copy column"
            }
          },
          "children": [
            {
              "type": "Text",
              "props": {
                "canDelete": true,
                "canEditName": true,
                "text": "Ship the story and the structure together",
                "tagName": "h2",
                "root": {
                  "preset": "h4",
                  "fontFamily": "var(--heading-font-family)",
                  "fontWeight": "font-bold",
                  "lineHeight": "leading-tight",
                  "color": "text-(--background)"
                },
                "mobile": {
                  "fontSize": "text-2xl",
                  "textAlign": "text-center"
                },
                "desktop": {
                  "fontSize": "text-4xl",
                  "textAlign": "text-right"
                },
                "custom": {
                  "displayName": "Heading"
                }
              }
            },
            {
              "type": "Text",
              "props": {
                "canDelete": true,
                "canEditName": true,
                "text": "PageHub keeps blocks, presets, and tokens wired the same way across pages, so your team spends less time fixing drift and more time publishing.",
                "tagName": "p",
                "root": {
                  "color": "text-(--background)",
                  "lineHeight": "leading-relaxed"
                },
                "mobile": {
                  "fontSize": "text-base",
                  "textAlign": "text-center",
                  "opacity": "opacity-90"
                },
                "desktop": {
                  "fontSize": "text-xl",
                  "textAlign": "text-right",
                  "lineHeight": "leading-snug",
                  "opacity": "opacity-90"
                },
                "custom": {
                  "displayName": "Body"
                }
              }
            }
          ]
        }
      ]
    }
  ]
}
